chainpipe/__init__.py
chainpipe/chain.py
chainpipe/logger.py
chainpipe/pipeline.py
chainpipe/timer.py
ChainPipe-0.1.1.dist-info/LICENSE.md
ChainPipe-0.1.1.dist-info/METADATA
ChainPipe-0.1.1.dist-info/WHEEL
ChainPipe-0.1.1.dist-info/top_level.txt
ChainPipe-0.1.1.dist-info/RECORD
