Metadata-Version: 2.1
Name: ChainPipe
Version: 0.1.1
Summary: A utility package for chaining and pipeline operations with enhanced logging and timing.
Home-page: https://github.com/ayman3000/ChainPipe
Author: Ayman Hamed
Author-email: ayman3000@gmail.com
Classifier: Development Status :: 3 - Alpha
Classifier: Intended Audience :: Developers
Classifier: Topic :: Software Development :: Libraries
Classifier: License :: OSI Approved :: MIT License
Classifier: Programming Language :: Python :: 3
Classifier: Programming Language :: Python :: 3.6
Classifier: Programming Language :: Python :: 3.7
Classifier: Programming Language :: Python :: 3.8
Classifier: Programming Language :: Python :: 3.9
Requires-Python: >=3.6
License-File: LICENSE.md
